{
    "task": [
        {
            "name": "AutoCombat",
            "label": "$task.AutoCombat.label",
            "entry": "Combat_Main",
            "controller": [
                "macOS",
                "macOS-Global"
            ],
            "group": [
                "combat"
            ],
            "option": [
                "CombatAutoTarget",
                "CombatUseLiberation",
                "CombatSwitchHealer",
                "CombatChisaDPS",
                "CombatIunoC6"
            ]
        }
    ],
    "option": {
        "CombatAutoTarget": {
            "type": "switch",
            "label": "$option.CombatAutoTarget.label",
            "default_case": "Yes",
            "cases": [
                {
                    "name": "Yes",
                    "pipeline_override": {
                        "Combat_Engage": {
                            "custom_action_param": {
                                "auto_target": true,
                                "use_liberation": true,
                                "switch_healer": false,
                                "chisa_dps": false,
                                "iuno_c6": false,
                                "dodge_cooldown_ms": 500,
                                "out_of_combat_switch_delay_ms": 2000,
                                "low_health_switch_delay_ms": 3000,
                                "concerto_switch_delay_ms": 8000,
                                "action_interval_ms": 120,
                                "auto_target_post_delay_ms": 200
                            }
                        }
                    }
                },
                {
                    "name": "No",
                    "pipeline_override": {
                        "Combat_Engage": {
                            "custom_action_param": {
                                "auto_target": false,
                                "use_liberation": true,
                                "switch_healer": false,
                                "chisa_dps": false,
                                "iuno_c6": false,
                                "dodge_cooldown_ms": 500,
                                "out_of_combat_switch_delay_ms": 2000,
                                "low_health_switch_delay_ms": 3000,
                                "concerto_switch_delay_ms": 8000,
                                "action_interval_ms": 120,
                                "auto_target_post_delay_ms": 200
                            }
                        }
                    }
                }
            ]
        },
        "CombatUseLiberation": {
            "type": "switch",
            "label": "$option.CombatUseLiberation.label",
            "default_case": "Yes",
            "cases": [
                {
                    "name": "Yes",
                    "pipeline_override": {
                        "Combat_Engage": {
                            "custom_action_param": {
                                "auto_target": true,
                                "use_liberation": true,
                                "switch_healer": false,
                                "chisa_dps": false,
                                "iuno_c6": false,
                                "dodge_cooldown_ms": 500,
                                "out_of_combat_switch_delay_ms": 2000,
                                "low_health_switch_delay_ms": 3000,
                                "concerto_switch_delay_ms": 8000,
                                "action_interval_ms": 120,
                                "auto_target_post_delay_ms": 200
                            }
                        }
                    }
                },
                {
                    "name": "No",
                    "pipeline_override": {
                        "Combat_Engage": {
                            "custom_action_param": {
                                "auto_target": true,
                                "use_liberation": false,
                                "switch_healer": false,
                                "chisa_dps": false,
                                "iuno_c6": false,
                                "dodge_cooldown_ms": 500,
                                "out_of_combat_switch_delay_ms": 2000,
                                "low_health_switch_delay_ms": 3000,
                                "concerto_switch_delay_ms": 8000,
                                "action_interval_ms": 120,
                                "auto_target_post_delay_ms": 200
                            }
                        }
                    }
                }
            ]
        },
        "CombatSwitchHealer": {
            "type": "switch",
            "label": "战斗结束后切换治疗角色",
            "default_case": "No",
            "cases": [
                {
                    "name": "Yes",
                    "pipeline_override": {
                        "Combat_Engage": {
                            "custom_action_param": {
                                "auto_target": true,
                                "use_liberation": true,
                                "switch_healer": true,
                                "chisa_dps": false,
                                "iuno_c6": false,
                                "dodge_cooldown_ms": 500,
                                "out_of_combat_switch_delay_ms": 2000,
                                "low_health_switch_delay_ms": 3000,
                                "concerto_switch_delay_ms": 8000,
                                "action_interval_ms": 120,
                                "auto_target_post_delay_ms": 200
                            }
                        }
                    }
                },
                {
                    "name": "No",
                    "pipeline_override": {
                        "Combat_Engage": {
                            "custom_action_param": {
                                "auto_target": true,
                                "use_liberation": true,
                                "switch_healer": false,
                                "chisa_dps": false,
                                "iuno_c6": false,
                                "dodge_cooldown_ms": 500,
                                "out_of_combat_switch_delay_ms": 2000,
                                "low_health_switch_delay_ms": 3000,
                                "concerto_switch_delay_ms": 8000,
                                "action_interval_ms": 120,
                                "auto_target_post_delay_ms": 200
                            }
                        }
                    }
                }
            ]
        },
        "CombatChisaDPS": {
            "type": "switch",
            "label": "Chisa 按主C站场",
            "default_case": "No",
            "cases": [
                {
                    "name": "Yes",
                    "pipeline_override": {
                        "Combat_Engage": {
                            "custom_action_param": {
                                "auto_target": true,
                                "use_liberation": true,
                                "switch_healer": false,
                                "chisa_dps": true,
                                "iuno_c6": false,
                                "dodge_cooldown_ms": 500,
                                "out_of_combat_switch_delay_ms": 2000,
                                "low_health_switch_delay_ms": 3000,
                                "concerto_switch_delay_ms": 8000,
                                "action_interval_ms": 120,
                                "auto_target_post_delay_ms": 200
                            }
                        }
                    }
                },
                {
                    "name": "No",
                    "pipeline_override": {
                        "Combat_Engage": {
                            "custom_action_param": {
                                "auto_target": true,
                                "use_liberation": true,
                                "switch_healer": false,
                                "chisa_dps": false,
                                "iuno_c6": false,
                                "dodge_cooldown_ms": 500,
                                "out_of_combat_switch_delay_ms": 2000,
                                "low_health_switch_delay_ms": 3000,
                                "concerto_switch_delay_ms": 8000,
                                "action_interval_ms": 120,
                                "auto_target_post_delay_ms": 200
                            }
                        }
                    }
                }
            ]
        },
        "CombatIunoC6": {
            "type": "switch",
            "label": "Iuno C6 按主C站场",
            "default_case": "No",
            "cases": [
                {
                    "name": "Yes",
                    "pipeline_override": {
                        "Combat_Engage": {
                            "custom_action_param": {
                                "auto_target": true,
                                "use_liberation": true,
                                "switch_healer": false,
                                "chisa_dps": false,
                                "iuno_c6": true,
                                "dodge_cooldown_ms": 500,
                                "out_of_combat_switch_delay_ms": 2000,
                                "low_health_switch_delay_ms": 3000,
                                "concerto_switch_delay_ms": 8000,
                                "action_interval_ms": 120,
                                "auto_target_post_delay_ms": 200
                            }
                        }
                    }
                },
                {
                    "name": "No",
                    "pipeline_override": {
                        "Combat_Engage": {
                            "custom_action_param": {
                                "auto_target": true,
                                "use_liberation": true,
                                "switch_healer": false,
                                "chisa_dps": false,
                                "iuno_c6": false,
                                "dodge_cooldown_ms": 500,
                                "out_of_combat_switch_delay_ms": 2000,
                                "low_health_switch_delay_ms": 3000,
                                "concerto_switch_delay_ms": 8000,
                                "action_interval_ms": 120,
                                "auto_target_post_delay_ms": 200
                            }
                        }
                    }
                }
            ]
        }
    }
}
